pyencry/__init__.py
pyencry/auto_decoder.py
pyencry/cli.py
pyencry/decoders.py
pyencry/encoders.py
pyencry/image_handler.py
pyencry/utils.py
py_encry-0.3.3.dist-info/METADATA
py_encry-0.3.3.dist-info/WHEEL
py_encry-0.3.3.dist-info/entry_points.txt
py_encry-0.3.3.dist-info/licenses/LICENSE
py_encry-0.3.3.dist-info/RECORD
